pytest_elements/__init__.py
pytest_elements/common/__init__.py
pytest_elements/common/config.py
pytest_elements/common/README.md
pytest_elements/common/sql_client.py
pytest_elements/common/ssh_client.py
pytest_elements/decorators/retry.py
pytest_elements/elements/__init__.py
pytest_elements/elements/anchor.py
pytest_elements/elements/button.py
pytest_elements/elements/canvas.py
pytest_elements/elements/checkbox.py
pytest_elements/elements/date_picker.py
pytest_elements/elements/div.py
pytest_elements/elements/dropdown.py
pytest_elements/elements/dropdown_option.py
pytest_elements/elements/dynamic_form.py
pytest_elements/elements/element_map.py
pytest_elements/elements/file_picker.py
pytest_elements/elements/fillable_element.py
pytest_elements/elements/form.py
pytest_elements/elements/form_component.py
pytest_elements/elements/formatting_element.py
pytest_elements/elements/h1.py
pytest_elements/elements/h2.py
pytest_elements/elements/h3.py
pytest_elements/elements/h4.py
pytest_elements/elements/h5.py
pytest_elements/elements/h6.py
pytest_elements/elements/heading.py
pytest_elements/elements/hyperlink.py
pytest_elements/elements/img.py
pytest_elements/elements/italic.py
pytest_elements/elements/label.py
pytest_elements/elements/list_item.py
pytest_elements/elements/null_element.py
pytest_elements/elements/ordered_list.py
pytest_elements/elements/page_element.py
pytest_elements/elements/radio_button.py
pytest_elements/elements/README.md
pytest_elements/elements/section.py
pytest_elements/elements/select.py
pytest_elements/elements/selection_element.py
pytest_elements/elements/span.py
pytest_elements/elements/table.py
pytest_elements/elements/table_body.py
pytest_elements/elements/table_data.py
pytest_elements/elements/table_foot.py
pytest_elements/elements/table_head.py
pytest_elements/elements/table_row.py
pytest_elements/elements/text_field.py
pytest_elements/elements/tile.py
pytest_elements/elements/tree.py
pytest_elements/elements/unordered_list.py
pytest_elements-1.0.2.dist-info/WHEEL
pytest_elements-1.0.2.dist-info/METADATA
pytest_elements-1.0.2.dist-info/RECORD
