Metadata-Version: 2.1
Name: pytest-elements
Version: 1.0.2
Summary: Tool to help automate user interfaces
Author: Jonah Caruso
Author-email: jayc035@yahoo.com
Requires-Python: >=3.7
Classifier: Programming Language :: Python :: 3
Classifier: Programming Language :: Python :: 3.7
Classifier: Programming Language :: Python :: 3.8
Requires-Dist: black (>=19.3b0,<20.0)
Requires-Dist: deprecation (>=2.0.7,<3.0.0)
Requires-Dist: faker (>=4.0,<5.0)
Requires-Dist: mypy (>=0.720,<0.721)
Requires-Dist: paramiko (>=2.7.1,<3.0.0)
Requires-Dist: pydoc-markdown (>=2.1.3,<3.0.0)
Requires-Dist: pymysql (>=0.9.3,<0.10.0)
Requires-Dist: pytest (>=5.4,<6.0)
Requires-Dist: pytest-recordings (>=0.4,<0.5)
Requires-Dist: selenium (>=3.141.0,<4.0.0)
